{
  "AAPL": {
    "price": 325.89,
    "currency": "USD"
  },
  "MSFT": {
    "price": 390.34,
    "currency": "USD"
  },
  "NVDA": {
    "price": 212.06,
    "currency": "USD"
  },
  "AVGO": {
    "price": 396.81,
    "currency": "USD"
  },
  "NASA": {
    "price": 23.27,
    "currency": "USD"
  },
  "IXHL": {
    "price": 3.12,
    "currency": "USD"
  },
  "SMH": {
    "price": 586.91,
    "currency": "USD"
  },
  "SPCX": {
    "price": 115.26,
    "currency": "USD"
  },
  "UBER": {
    "price": 70.33,
    "currency": "USD"
  },
  "RKLB": {
    "price": 69.75,
    "currency": "USD"
  },
  "LUNR": {
    "price": 14.09,
    "currency": "USD"
  },
  "PL": {
    "price": 22.6,
    "currency": "USD"
  },
  "RDW": {
    "price": 8.99,
    "currency": "USD"
  },
  "BKSY": {
    "price": 22.49,
    "currency": "USD"
  },
  "ASTS": {
    "price": 61.95,
    "currency": "USD"
  },
  "SPIR": {
    "price": 11.43,
    "currency": "USD"
  },
  "BTC-USD": {
    "price": 65576.1484,
    "currency": "USD"
  },
  "ETH-USD": {
    "price": 1918.61,
    "currency": "USD"
  },
  "ADANIENT.NS": {
    "price": 3085.8,
    "currency": "INR"
  },
  "ADANIGREEN.NS": {
    "price": 1397.4,
    "currency": "INR"
  },
  "ADANIPORTS.NS": {
    "price": 1801.4,
    "currency": "INR"
  },
  "ADANIPOWER.NS": {
    "price": 215.4,
    "currency": "INR"
  },
  "AMBUJACEM.NS": {
    "price": 428.15,
    "currency": "INR"
  },
  "APOLLOHOSP.NS": {
    "price": 8893.0,
    "currency": "INR"
  },
  "ASIANPAINT.NS": {
    "price": 2684.1001,
    "currency": "INR"
  },
  "AUROPHARMA.NS": {
    "price": 1536.7,
    "currency": "INR"
  },
  "AXISBANK.NS": {
    "price": 1234.9,
    "currency": "INR"
  },
  "BAJAJ-AUTO.NS": {
    "price": 11271.5,
    "currency": "INR"
  },
  "BAJFINANCE.NS": {
    "price": 1049.7,
    "currency": "INR"
  },
  "BAJAJFINSV.NS": {
    "price": 1888.2,
    "currency": "INR"
  },
  "BANKBARODA.NS": {
    "price": 244.8,
    "currency": "INR"
  },
  "BEL.NS": {
    "price": 405.3,
    "currency": "INR"
  },
  "BHARTIARTL.NS": {
    "price": 1935.3,
    "currency": "INR"
  },
  "BHEL.NS": {
    "price": 413.15,
    "currency": "INR"
  },
  "BPCL.NS": {
    "price": 316.25,
    "currency": "INR"
  },
  "BRITANNIA.NS": {
    "price": 5465.0,
    "currency": "INR"
  },
  "CANBK.NS": {
    "price": 126.79,
    "currency": "INR"
  },
  "CIPLA.NS": {
    "price": 1413.0,
    "currency": "INR"
  },
  "COALINDIA.NS": {
    "price": 427.8,
    "currency": "INR"
  },
  "DABUR.NS": {
    "price": 426.3,
    "currency": "INR"
  },
  "DIVISLAB.NS": {
    "price": 7364.0,
    "currency": "INR"
  },
  "DLF.NS": {
    "price": 655.3,
    "currency": "INR"
  },
  "DRREDDY.NS": {
    "price": 1154.6,
    "currency": "INR"
  },
  "EICHERMOT.NS": {
    "price": 7693.5,
    "currency": "INR"
  },
  "GAIL.NS": {
    "price": 171.72,
    "currency": "INR"
  },
  "GODREJCP.NS": {
    "price": 1081.2,
    "currency": "INR"
  },
  "GRASIM.NS": {
    "price": 3151.6001,
    "currency": "INR"
  },
  "HAL.NS": {
    "price": 4572.0,
    "currency": "INR"
  },
  "HAVELLS.NS": {
    "price": 1214.3,
    "currency": "INR"
  },
  "HCLTECH.NS": {
    "price": 1239.6,
    "currency": "INR"
  },
  "HDFCBANK.NS": {
    "price": 746.8,
    "currency": "INR"
  },
  "HDFCLIFE.NS": {
    "price": 550.65,
    "currency": "INR"
  },
  "HEROMOTOCO.NS": {
    "price": 5154.5,
    "currency": "INR"
  },
  "HINDALCO.NS": {
    "price": 960.1,
    "currency": "INR"
  },
  "HINDUNILVR.NS": {
    "price": 2160.0,
    "currency": "INR"
  },
  "ICICIBANK.NS": {
    "price": 1440.3,
    "currency": "INR"
  },
  "ICICIGI.NS": {
    "price": 1586.8,
    "currency": "INR"
  },
  "ICICIPRULI.NS": {
    "price": 496.5,
    "currency": "INR"
  },
  "INDIGO.NS": {
    "price": 5115.0,
    "currency": "INR"
  },
  "INDUSINDBK.NS": {
    "price": 1016.2,
    "currency": "INR"
  },
  "INFY.NS": {
    "price": 1043.8,
    "currency": "INR"
  },
  "IOC.NS": {
    "price": 142.13,
    "currency": "INR"
  },
  "IRCTC.NS": {
    "price": 491.7,
    "currency": "INR"
  },
  "ITC.NS": {
    "price": 281.65,
    "currency": "INR"
  },
  "JINDALSTEL.NS": {
    "price": 1049.7,
    "currency": "INR"
  },
  "JSWENERGY.NS": {
    "price": 560.5,
    "currency": "INR"
  },
  "JSWSTEEL.NS": {
    "price": 1265.7,
    "currency": "INR"
  },
  "JUBLFOOD.NS": {
    "price": 418.85,
    "currency": "INR"
  },
  "KOTAKBANK.NS": {
    "price": 384.4,
    "currency": "INR"
  },
  "LT.NS": {
    "price": 3820.8999,
    "currency": "INR"
  },
  "M&M.NS": {
    "price": 3237.8,
    "currency": "INR"
  },
  "MARICO.NS": {
    "price": 856.05,
    "currency": "INR"
  },
  "MARUTI.NS": {
    "price": 13552.0,
    "currency": "INR"
  },
  "MOTHERSON.NS": {
    "price": 146.3,
    "currency": "INR"
  },
  "NESTLEIND.NS": {
    "price": 1463.9,
    "currency": "INR"
  },
  "NTPC.NS": {
    "price": 347.55,
    "currency": "INR"
  },
  "ONGC.NS": {
    "price": 252.65,
    "currency": "INR"
  },
  "PAYTM.NS": {
    "price": 1280.8,
    "currency": "INR"
  },
  "PIDILITIND.NS": {
    "price": 1589.5,
    "currency": "INR"
  },
  "PFC.NS": {
    "price": 410.5,
    "currency": "INR"
  },
  "PNB.NS": {
    "price": 110.7,
    "currency": "INR"
  },
  "POWERGRID.NS": {
    "price": 289.75,
    "currency": "INR"
  },
  "RECLTD.NS": {
    "price": 359.6,
    "currency": "INR"
  },
  "RELIANCE.NS": {
    "price": 1286.4,
    "currency": "INR"
  },
  "SBILIFE.NS": {
    "price": 1813.4,
    "currency": "INR"
  },
  "SHREECEM.NS": {
    "price": 27020.0,
    "currency": "INR"
  },
  "SIEMENS.NS": {
    "price": 3682.1001,
    "currency": "INR"
  },
  "SUNPHARMA.NS": {
    "price": 1944.0,
    "currency": "INR"
  },
  "TATACONSUM.NS": {
    "price": 1103.8,
    "currency": "INR"
  },
  "TATAPOWER.NS": {
    "price": 377.85,
    "currency": "INR"
  },
  "TATASTEEL.NS": {
    "price": 185.11,
    "currency": "INR"
  },
  "TCS.NS": {
    "price": 2213.0,
    "currency": "INR"
  },
  "TECHM.NS": {
    "price": 1562.4,
    "currency": "INR"
  },
  "TITAN.NS": {
    "price": 4691.2002,
    "currency": "INR"
  },
  "TORNTPHARM.NS": {
    "price": 5021.0,
    "currency": "INR"
  },
  "TRENT.NS": {
    "price": 2900.3999,
    "currency": "INR"
  },
  "TVSMOTOR.NS": {
    "price": 3946.3,
    "currency": "INR"
  },
  "ULTRACEMCO.NS": {
    "price": 11907.0,
    "currency": "INR"
  },
  "UNIONBANK.NS": {
    "price": 169.25,
    "currency": "INR"
  },
  "VEDL.NS": {
    "price": 266.9,
    "currency": "INR"
  },
  "WIPRO.NS": {
    "price": 174.64,
    "currency": "INR"
  },
  "CGPOWER.NS": {
    "price": 907.65,
    "currency": "INR"
  },
  "CROMPTON.NS": {
    "price": 252.5,
    "currency": "INR"
  },
  "DEEPAKNTR.NS": {
    "price": 1678.8,
    "currency": "INR"
  },
  "DIXON.NS": {
    "price": 14007.0,
    "currency": "INR"
  },
  "DMART.NS": {
    "price": 4071.3999,
    "currency": "INR"
  },
  "E2E.NS": {
    "price": 492.1,
    "currency": "INR"
  },
  "HDFCSML250.NS": {
    "price": 179.54,
    "currency": "INR"
  },
  "IREDA.NS": {
    "price": 120.53,
    "currency": "INR"
  },
  "IRFC.NS": {
    "price": 87.33,
    "currency": "INR"
  },
  "JIOFIN.NS": {
    "price": 235.08,
    "currency": "INR"
  },
  "KPITTECH.NS": {
    "price": 553.15,
    "currency": "INR"
  },
  "KWIL.NS": {
    "price": 32.28,
    "currency": "INR"
  },
  "LICI.NS": {
    "price": 423.75,
    "currency": "INR"
  },
  "MID150CASE.NS": {
    "price": 11.53,
    "currency": "INR"
  },
  "MAFANG.NS": {
    "price": 197.77,
    "currency": "INR"
  },
  "NIFTYBEES.NS": {
    "price": 273.2,
    "currency": "INR"
  },
  "POLYCAB.NS": {
    "price": 9087.0,
    "currency": "INR"
  },
  "RVNL.NS": {
    "price": 222.98,
    "currency": "INR"
  },
  "SETFNN50.NS": {
    "price": 776.08,
    "currency": "INR"
  },
  "TMPV.NS": {
    "price": 327.9,
    "currency": "INR"
  },
  "TMCV.NS": {
    "price": 407.05,
    "currency": "INR"
  },
  "TRIDENT.NS": {
    "price": 25.28,
    "currency": "INR"
  },
  "YESBANK.NS": {
    "price": 23.06,
    "currency": "INR"
  },
  "ZENTEC.NS": {
    "price": 1786.0,
    "currency": "INR"
  },
  "updatedAt": "2026-07-23T05:13:58.301081+00:00"
}